sage_qrcode/__init__.py
sage_qrcode/admin/__init__.py
sage_qrcode/admin/actions/__init__.py
sage_qrcode/admin/actions/download.py
sage_qrcode/admin/barcode.py
sage_qrcode/admin/base.py
sage_qrcode/admin/contact.py
sage_qrcode/admin/payment.py
sage_qrcode/admin/social_media.py
sage_qrcode/apps.py
sage_qrcode/check.py
sage_qrcode/forms/__init__.py
sage_qrcode/forms/forms.py
sage_qrcode/helpers/__init__.py
sage_qrcode/helpers/filters/__init__.py
sage_qrcode/helpers/filters/qrcodeadmin.py
sage_qrcode/helpers/type.py
sage_qrcode/helpers/validators/__init__.py
sage_qrcode/helpers/validators/bitcoin.py
sage_qrcode/helpers/validators/event.py
sage_qrcode/helpers/validators/geo_location.py
sage_qrcode/helpers/validators/iban.py
sage_qrcode/helpers/validators/image.py
sage_qrcode/helpers/validators/phone_number.py
sage_qrcode/helpers/validators/socials.py
sage_qrcode/migrations/__init__.py
sage_qrcode/mixins/__init__.py
sage_qrcode/mixins/time.py
sage_qrcode/models/__init__.py
sage_qrcode/models/barcode.py
sage_qrcode/models/bitcoin.py
sage_qrcode/models/card.py
sage_qrcode/models/epc.py
sage_qrcode/models/qrcode.py
sage_qrcode/models/social_media.py
sage_qrcode/models/wifi.py
sage_qrcode/service/__init__.py
sage_qrcode/service/barcode.py
sage_qrcode/service/base.py
sage_qrcode/service/contact_qrcode.py
sage_qrcode/service/icons/gram.png
sage_qrcode/service/icons/instagram.png
sage_qrcode/service/icons/linkedin.png
sage_qrcode/service/icons/logo.png
sage_qrcode/service/icons/meta.png
sage_qrcode/service/icons/skype.png
sage_qrcode/service/icons/snapchat.png
sage_qrcode/service/icons/social.png
sage_qrcode/service/icons/ti.png
sage_qrcode/service/icons/witter.png
sage_qrcode/service/icons/youtube.png
sage_qrcode/service/payment_qrcode.py
sage_qrcode/service/social_qrcode.py
sage_qrcode/tests/__init__.py
sage_qrcode/tests/conftest.py
sage_qrcode/tests/service/test_barcode.py
sage_qrcode/tests/service/test_contact_qrcode.py
sage_qrcode/tests/service/test_payment_qrcode.py
django_sage_qrcode-0.1.0.dist-info/LICENSE
django_sage_qrcode-0.1.0.dist-info/METADATA
django_sage_qrcode-0.1.0.dist-info/WHEEL
django_sage_qrcode-0.1.0.dist-info/RECORD
