Metadata-Version: 2.1
Name: django-sage-qrcode
Version: 0.1.0
Summary: A project for QR code generation and NFC integration
Author: Radin Ghahremani
Author-email: radin@sageteam.org
Requires-Python: >=3.11,<4.0
Classifier: Programming Language :: Python :: 3
Classifier: Programming Language :: Python :: 3.11
Classifier: Programming Language :: Python :: 3.12
Provides-Extra: docs
Requires-Dist: django (>=5.0.6,<6.0.0)
Requires-Dist: django-colorfield (>=0.11.0,<0.12.0)
Requires-Dist: django-polymorphic (>=3.1.0,<4.0.0)
Requires-Dist: djangorestframework (>=3.15.2,<4.0.0)
Requires-Dist: ndef (>=0.2,<0.3)
Requires-Dist: ndeflib (>=0.3.3,<0.4.0)
Requires-Dist: nfcpy (>=1.0.4,<2.0.0)
Requires-Dist: pyshorteners (>=1.0.1,<2.0.0)
Requires-Dist: python-barcode (>=0.15.1,<0.16.0)
Requires-Dist: qrcode-artistic (>=3.0.2,<4.0.0)
Requires-Dist: sengo (>=0.0.2,<0.0.3)
